setup.py
anchor/__init__.py
anchor/asyncflow/__init__.py
anchor/strings/__init__.py
anchor/strings/paginator.py
anchor/strings/regexp.py
anchor/strings/search.py
anchor/strings/cryptography/__init__.py
anchor/strings/cryptography/custom_b64.py
anchor/strings/parsing/__init__.py
anchor/strings/parsing/ranges.py
anchor/strings/parsing/objectnotation/__init__.py
anchor/strings/parsing/objectnotation/quickson.py
anchor/strings/parsing/objectnotation/regexson.py
anchor_kr.egg-info/PKG-INFO
anchor_kr.egg-info/SOURCES.txt
anchor_kr.egg-info/dependency_links.txt
anchor_kr.egg-info/top_level.txt