Metadata-Version: 2.1
Name: anchor-kr
Version: 0.1.3
Summary: Me, you and anchor make your scraper complete.
Home-page: https://github.com/justfoolingaround/anchor
Author: kr@justfoolingaround
Author-email: kr.justfoolingaround@gmail.com
License: UNKNOWN
Platform: UNKNOWN
